Metadata-Version: 2.1
Name: package-kanha
Version: 0.0.1
Summary: This is very basic calculator
Home-page: UNKNOWN
Author: kanhaiya kumar
Author-email: kanhaiya20@iitk.ac.in
License: UNKNOWN
Keywords: calculator
Platform: UNKNOWN
Classifier: Development Status :: 5 - Production/Stable
Classifier: Intended Audience :: Education
Classifier: Operating System :: Microsoft :: Windows :: Windows 10
Classifier: License :: OSI Approved :: MIT License
Classifier: Programming Language :: Python :: 3.9
License-File: license.txt
